wypeditor/__init__.py
wypeditor/__main__.py
wypeditor/main.py
wypeditor-0.1.1.dist-info/entry_points.txt
wypeditor-0.1.1.dist-info/LICENSE
wypeditor-0.1.1.dist-info/METADATA
wypeditor-0.1.1.dist-info/WHEEL
wypeditor-0.1.1.dist-info/RECORD
