Metadata-Version: 2.1
Name: wypeditor
Version: 0.1.1
Summary: An Image Editor based on wyper
License: MIT
Author: Amaan
Author-email: 71920621+amaank404@users.noreply.github.com
Requires-Python: >=3.11,<4.0
Classifier: License :: OSI Approved :: MIT License
Classifier: Programming Language :: Python :: 3
Classifier: Programming Language :: Python :: 3.11
Requires-Dist: darkdetect (>=0.8.0,<0.9.0)
Requires-Dist: pygame (>=2,<3)
Requires-Dist: wyper (>=0.1.2)
